ultravox_vllm/__init__.py
ultravox_vllm/models/ultravox.py
ultravox_vllm/models/whisper_streaming.py
ultravox_vllm/monkeypatch.py
ultravox_vllm/serve.py
ultravox_vllm-0.5.4.1.dist-info/METADATA
ultravox_vllm-0.5.4.1.dist-info/WHEEL
ultravox_vllm-0.5.4.1.dist-info/RECORD
