Metadata-Version: 2.1
Name: ultravox-vllm
Version: 0.5.4.1
Summary: 
Author: Peter Salas
Author-email: peter@fixie.ai
Requires-Python: >=3.10,<4.0
Classifier: Programming Language :: Python :: 3
Classifier: Programming Language :: Python :: 3.10
Classifier: Programming Language :: Python :: 3.11
Classifier: Programming Language :: Python :: 3.12
Requires-Dist: librosa (>=0.10.2.post1,<0.11.0)
Requires-Dist: torchaudio (>=2.4.0,<3.0.0)
Requires-Dist: vllm (==0.5.4)
Requires-Dist: wrapt (>=1.16.0,<2.0.0)
